{"commitInfo":{"timestamp":1600950876689,"operation":"UPDATE","operationParameters":{},"readVersion":113,"isBlindAppend":false,"operationMetrics":{"numRemovedFiles":"1","numAddedFiles":"1","numUpdatedRows":"1000","numCopiedRows":"0"}}}
{"remove":{"path":"part-00000-191ad8ba-34c2-4140-8b28-27bcbf3de384-c000.snappy.parquet","deletionTimestamp":1600950876430,"dataChange":true}}
{"add":{"path":"part-00000-0d9a2201-b49b-4b38-9418-9ab4ca3573f6-c000.snappy.parquet","partitionValues":{},"size":78305,"modificationTime":1600950876671,"dataChange":true}}
