{"commitInfo":{"timestamp":1600933370974,"operation":"WRITE","operationParameters":{"mode":"Overwrite","partitionBy":"[]"},"readVersion":88,"isBlindAppend":false,"operationMetrics":{"numFiles":"1","numOutputBytes":"78304","numOutputRows":"1000"}}}
{"add":{"path":"part-00000-8615337d-7a1d-406d-8398-7502f082c89f-c000.snappy.parquet","partitionValues":{},"size":78304,"modificationTime":1600933369241,"dataChange":true}}
{"remove":{"path":"part-00000-6468b1da-5acd-4e38-8ffb-587d33aa8029-c000.snappy.parquet","deletionTimestamp":1600933370974,"dataChange":true}}
