{"commitInfo":{"timestamp":1600950512562,"operation":"WRITE","operationParameters":{"mode":"Overwrite","partitionBy":"[]"},"readVersion":61,"isBlindAppend":false,"operationMetrics":{"numFiles":"1","numOutputBytes":"78304","numOutputRows":"1000"}}}
{"add":{"path":"part-00000-19aefc66-5fe2-4ac0-b358-1367a6329ead-c000.snappy.parquet","partitionValues":{},"size":78304,"modificationTime":1600950510534,"dataChange":true}}
{"remove":{"path":"part-00000-56e76d7f-35d0-4f61-b7df-98233c9d80f3-c000.snappy.parquet","deletionTimestamp":1600950512562,"dataChange":true}}
